{
	"cursor": "/Users/latona2/bitbucket/sap-api-integrations-production-routing-reads/SAP_API_Caller/caller.go#L87",
	"function": "sap-api-integrations-production-routing-reads/SAP_API_Caller.(*SAPAPICaller).Header",
	"level": "INFO",
	"message": [
		{
			"ProductionRoutingGroup": "40000060",
			"ProductionRouting": "1",
			"ProductionRoutingSequence": "0",
			"ProductionRoutingSqncIntVers": "1",
			"ChangeNumber": "",
			"ValidityStartDate": "2021-02-01T09:00:00+09:00",
			"ValidityEndDate": "9999-12-31T09:00:00+09:00",
			"SequenceCategory": "0",
			"BillOfOperationsRefSequence": "",
			"MinimumLotSizeQuantity": "1.000",
			"MaximumLotSizeQuantity": "99999999.000",
			"BillOfOperationsUnit": "",
			"SequenceText": "",
			"CreationDate": "2021-02-01T09:00:00+09:00",
			"LastChangeDate": "2021-02-01T09:00:00+09:00",
			"to_Operation": "https://sandbox.api.sap.com/s4hanacloud/sap/opu/odata/sap/API_PRODUCTION_ROUTING/ProductionRoutingSequence(ProductionRoutingGroup='40000060',ProductionRouting='1',ProductionRoutingSequence='0',ProductionRoutingSqncIntVers='1')/to_Operation"
		}
	],
	"time": "2022-01-28T14:08:57+09:00"
}
